setup.py
mess_server_prj_Ruslan.egg-info/PKG-INFO
mess_server_prj_Ruslan.egg-info/SOURCES.txt
mess_server_prj_Ruslan.egg-info/dependency_links.txt
mess_server_prj_Ruslan.egg-info/requires.txt
mess_server_prj_Ruslan.egg-info/top_level.txt
server/__init__.py
server/server.py
server/server_database.py
server/server_gui.py
server/common/__init__.py
server/common/decos.py
server/common/descriptors.py
server/common/errors.py
server/common/metaclasses.py
server/common/utils.py
server/common/vars.py
server/unit_tests/__init__.py
server/unit_tests/sock_test.py
server/unit_tests/test_client.py
server/unit_tests/test_server.py
server/unit_tests/test_utils.py