Metadata-Version: 1.0
Name: mess-server-prj-Ruslan
Version: 0.0.1
Summary: mess_server_prj
Home-page: UNKNOWN
Author: Ruslan
Author-email: huzin.ruslan@mail.ru
License: UNKNOWN
Platform: UNKNOWN
